networking_generic_switch/__init__.py
networking_generic_switch/_i18n.py
networking_generic_switch/batching.py
networking_generic_switch/config.py
networking_generic_switch/exceptions.py
networking_generic_switch/generic_switch_mech.py
networking_generic_switch/generic_switch_sg.py
networking_generic_switch/locking.py
networking_generic_switch/trunk_driver.py
networking_generic_switch/utils.py
networking_generic_switch/devices/__init__.py
networking_generic_switch/devices/utils.py
networking_generic_switch/devices/netmiko_devices/__init__.py
networking_generic_switch/devices/netmiko_devices/arista.py
networking_generic_switch/devices/netmiko_devices/aruba.py
networking_generic_switch/devices/netmiko_devices/brocade.py
networking_generic_switch/devices/netmiko_devices/cisco.py
networking_generic_switch/devices/netmiko_devices/cisco300.py
networking_generic_switch/devices/netmiko_devices/cumulus.py
networking_generic_switch/devices/netmiko_devices/dell.py
networking_generic_switch/devices/netmiko_devices/fake.py
networking_generic_switch/devices/netmiko_devices/hpe.py
networking_generic_switch/devices/netmiko_devices/huawei.py
networking_generic_switch/devices/netmiko_devices/huawei_vrpv8.py
networking_generic_switch/devices/netmiko_devices/juniper.py
networking_generic_switch/devices/netmiko_devices/mellanox_mlnxos.py
networking_generic_switch/devices/netmiko_devices/nokia.py
networking_generic_switch/devices/netmiko_devices/ovs.py
networking_generic_switch/devices/netmiko_devices/pluribus.py
networking_generic_switch/devices/netmiko_devices/ruijie.py
networking_generic_switch/devices/netmiko_devices/smc.py
networking_generic_switch/devices/netmiko_devices/sonic.py
networking_generic_switch/tests/__init__.py
networking_generic_switch/tests/unit/__init__.py
networking_generic_switch/tests/unit/test_batching.py
networking_generic_switch/tests/unit/test_config.py
networking_generic_switch/tests/unit/test_devices.py
networking_generic_switch-8.0.0.dist-info/AUTHORS
networking_generic_switch-8.0.0.dist-info/LICENSE
networking_generic_switch-8.0.0.dist-info/METADATA
networking_generic_switch-8.0.0.dist-info/WHEEL
networking_generic_switch-8.0.0.dist-info/entry_points.txt
networking_generic_switch-8.0.0.dist-info/pbr.json
networking_generic_switch-8.0.0.dist-info/top_level.txt
networking_generic_switch-8.0.0.dist-info/RECORD
