Metadata-Version: 2.1
Name: networking-generic-switch
Version: 8.0.0
Summary: Generic Switch ML2 Neutron Driver
Home-page: https://docs.openstack.org/networking-generic-switch/latest/
Author: OpenStack
Author-email: openstack-discuss@lists.openstack.org
Classifier: Environment :: OpenStack
Classifier: Intended Audience :: System Administrators
Classifier: Intended Audience :: Information Technology
Classifier: License :: OSI Approved :: Apache Software License
Classifier: Operating System :: OS Independent
Classifier: Programming Language :: Python
Classifier: Programming Language :: Python :: Implementation :: CPython
Classifier: Programming Language :: Python :: 3 :: Only
Classifier: Programming Language :: Python :: 3
Classifier: Programming Language :: Python :: 3.10
Classifier: Programming Language :: Python :: 3.11
Classifier: Programming Language :: Python :: 3.12
Requires-Python: >=3.10
License-File: LICENSE
License-File: AUTHORS
Requires-Dist: etcd3gw >=2.1.0
Requires-Dist: oslo.service[threading] >=4.2.0
Requires-Dist: stevedore >=1.20.0
Requires-Dist: netmiko >=4.1.1
Requires-Dist: neutron >=13.0.0.0b1
Requires-Dist: neutron-lib >=1.18.0
Requires-Dist: oslo.config >=5.2.0
Requires-Dist: oslo.i18n >=3.15.3
Requires-Dist: oslo.log >=3.36.0
Requires-Dist: oslo.utils >=3.40.2
Requires-Dist: tenacity >=6.0.0
Requires-Dist: tooz >=2.5.1
